pytest_playwright/__init__.py
pytest_playwright/py.typed
pytest_playwright/pytest_playwright.py
pytest_playwright-0.7.1.dist-info/LICENSE
pytest_playwright-0.7.1.dist-info/METADATA
pytest_playwright-0.7.1.dist-info/WHEEL
pytest_playwright-0.7.1.dist-info/entry_points.txt
pytest_playwright-0.7.1.dist-info/top_level.txt
pytest_playwright-0.7.1.dist-info/RECORD
